pyg_bond/__init__.py
pyg_bond/_base.py
pyg_bond/_bond.py
pyg_bond/_bond_futures.py
pyg_bond/_cds.py
pyg_bond/_ilb.py
pyg_bond-0.0.19.dist-info/licenses/LICENSE.txt
pyg_bond-0.0.19.dist-info/METADATA
pyg_bond-0.0.19.dist-info/WHEEL
pyg_bond-0.0.19.dist-info/top_level.txt
pyg_bond-0.0.19.dist-info/RECORD
