Metadata-Version: 2.4
Name: pyg-bond
Version: 0.0.19
Summary: Utilities for converting australian bill/bond futures to price. Also simple price to yield and yield to price.
Home-page: https://github.com/gityoav/pyg-bond
Author: Yoav Git
Author-email: yoav.git@gmail.com
Project-URL: Bug Tracker, https://github.com/gityoav/pyg-bond/issues
Classifier: Programming Language :: Python :: 3
Classifier: License :: OSI Approved :: GNU General Public License v3 (GPLv3)
Classifier: Operating System :: OS Independent
Requires-Python: >=3.6
License-File: LICENSE.txt
Requires-Dist: numpy
Requires-Dist: pandas
Requires-Dist: pyg-base
Dynamic: license-file
